liken/__init__.py
liken/_constants.py
liken/_custom.py
liken/_dataframe.py
liken/_executors.py
liken/_strats_library.py
liken/_strats_manager.py
liken/_types.py
liken/_validators.py
liken/custom/__init__.py
liken/datasets/__init__.py
liken/datasets/synthetic.py
liken/dedupe.py
liken/rules/__init__.py
liken-0.1.1.dist-info/METADATA
liken-0.1.1.dist-info/WHEEL
liken-0.1.1.dist-info/licenses/LICENSE
liken-0.1.1.dist-info/licenses/NOTICE
liken-0.1.1.dist-info/RECORD
