Metadata-Version: 2.4
Name: liken
Version: 0.1.1
Summary: A Python library for near deduplication and record linkage.
License: Apache-2.0
License-File: LICENSE
License-File: NOTICE
Keywords: duplicates,deduplication,record linkage,canonicalization
Author: VictorAut
Requires-Python: >=3.11,<3.14
Classifier: Development Status :: 2 - Pre-Alpha
Classifier: Intended Audience :: Developers
Classifier: Intended Audience :: Science/Research
Classifier: License :: OSI Approved :: Apache Software License
Classifier: Programming Language :: Python :: 3
Classifier: Programming Language :: Python :: 3.11
Classifier: Programming Language :: Python :: 3.12
Classifier: Programming Language :: Python :: 3.13
Classifier: Topic :: Software Development :: Libraries :: Python Modules
Requires-Dist: datasketch (>=1.8.0,<2.0.0)
Requires-Dist: networkx (>=3.6.1,<4.0.0)
Requires-Dist: pandas (>=2.2.3,<3.0.0)
Requires-Dist: polars (>=1.24.0,<2.0.0)
Requires-Dist: pyspark (>=3.5.5,<4.0.0)
Requires-Dist: rapidfuzz (>=3.12.2,<4.0.0)
Requires-Dist: scikit-learn (>=1.6.1,<2.0.0)
Requires-Dist: sparse-dot-topn (>=1.1.5,<2.0.0)
Requires-Dist: typing-extensions (>=4.13.0,<5.0.0)
Project-URL: Documentation, https://victorautonell-oiry.me/liken/liken.html
Project-URL: Repository, https://github.com/VictorAut/liken/
